[
  {
    "name": "CamScanner 20-04-2026 13.03_4.jpg",
    "type": "photo",
    "telegramFileId": "BQACAgUAAxkDAAMDagQM01wQS-MsvSlGnN8SHJSXh0IAAkwdAAKbMCFUsKgjWQTDuyQ7BA",
    "size": 1290076,
    "uploadedAt": 1778650324059
  },
  {
    "name": "CamScanner 20-04-2026 13.03_5.jpg",
    "type": "photo",
    "telegramFileId": "BQACAgUAAxkDAAMEagQM1RbdQW9YsXMHyN97CciUtCoAAk0dAAKbMCFU7QeJeIskXKI7BA",
    "size": 1465366,
    "uploadedAt": 1778650325642
  },
  {
    "name": "PSKT4C-07W006.pdf",
    "type": "docs",
    "telegramFileId": "BQACAgUAAxkDAAMFagQNEVoD8mgRLw-vzca0qy9yDvUAAk4dAAKbMCFUXdMrx6mKn087BA",
    "size": 73188,
    "uploadedAt": 1778650385283
  },
  {
    "name": "promt _1778650560518.txt",
    "type": "text",
    "telegramFileId": "BQACAgUAAxkDAAMHagQNwVE5VMwYvyEndAuxFcuxdogAAlAdAAKbMCFUa899Lci7Rj07BA",
    "size": 1554,
    "uploadedAt": 1778650562006
  },
  {
    "name": "Gemini_Generated_Image_xzd7ucxzd7ucxzd7 (1).png",
    "type": "photo",
    "telegramFileId": "BQACAgUAAxkDAAMJagQQXJb4rsDdsiHMJZ6MOeGyNqQAAlIdAAKbMCFU5Jfl-IozmvA7BA",
    "size": 556306,
    "uploadedAt": 1778651228707
  },
  {
    "id": "1778681469414_mqzyi1w",
    "name": "CamScanner 20-04-2026 13.03_8.jpg",
    "type": "photo",
    "telegramFileId": "AgACAgUAAxkDAAMWagSGfYXytlM0WutpwvcX6mmqOTYAApsSaxubMCFUU8vTtHpIbnkBAAMCAAN3AAM7BA",
    "thumbTelegramFileId": null,
    "size": 1423623,
    "folderId": null,
    "ownerUsername": "admin",
    "uploadedAt": 1778681469414
  },
  {
    "id": "1778681473408_xv7inxj",
    "name": "CamScanner 20-04-2026 10.35_111.jpg",
    "type": "photo",
    "telegramFileId": "AgACAgUAAxkDAAMXagSGgNjvMJy-mjsb9sJ0011UmUEAApwSaxubMCFUpl7BK46Zx68BAAMCAAN3AAM7BA",
    "thumbTelegramFileId": null,
    "size": 1570610,
    "folderId": null,
    "ownerUsername": "admin",
    "uploadedAt": 1778681473408
  },
  {
    "id": "1778681477373_kzazrff",
    "name": "CamScanner 20-04-2026 10.35_114.jpg",
    "type": "photo",
    "telegramFileId": "AgACAgUAAxkDAAMYagSGhH-DNwgYNpdYPaj-XcydwgYAAp0SaxubMCFUGfmwWRHKxAkBAAMCAAN3AAM7BA",
    "thumbTelegramFileId": null,
    "size": 1018057,
    "folderId": null,
    "ownerUsername": "admin",
    "uploadedAt": 1778681477373
  },
  {
    "id": "1778681478951_nss653l",
    "name": "CamScanner 20-04-2026 10.35_115.jpg",
    "type": "photo",
    "telegramFileId": "AgACAgUAAxkDAAMZagSGhh0L39V1UCK3IFKsbCWyS9cAAp4SaxubMCFUb620C5zKnooBAAMCAAN3AAM7BA",
    "thumbTelegramFileId": null,
    "size": 1343001,
    "folderId": null,
    "ownerUsername": "admin",
    "uploadedAt": 1778681478951
  },
  {
    "id": "1778681483368_ied1jjk",
    "name": "CamScanner 20-04-2026 10.35_116.jpg",
    "type": "photo",
    "telegramFileId": "AgACAgUAAxkDAAMaagSGig9NGqfR_M-v0YHHIaUPstcAAp8SaxubMCFUWZdZG9whZS8BAAMCAAN3AAM7BA",
    "thumbTelegramFileId": null,
    "size": 1179911,
    "folderId": null,
    "ownerUsername": "admin",
    "uploadedAt": 1778681483368
  },
  {
    "id": "1778681486117_795pd0z",
    "name": "CamScanner 20-04-2026 10.35_130.jpg",
    "type": "photo",
    "telegramFileId": "AgACAgUAAxkDAAMbagSGjSGIxUq7IjRco8CI5f4bolYAAqASaxubMCFUh6L1KqbsJhEBAAMCAAN3AAM7BA",
    "thumbTelegramFileId": null,
    "size": 1319037,
    "folderId": null,
    "ownerUsername": "admin",
    "uploadedAt": 1778681486118
  },
  {
    "id": "1778681486934_v1ac20r",
    "name": "nid-9165182974.pdf",
    "type": "docs",
    "telegramFileId": "BQACAgUAAxkDAAMcagSGjkG1KBNjThGZHFJ-opbqOBkAAoAeAAKbMCFUF2_IPQjLqWc7BA",
    "thumbTelegramFileId": null,
    "size": 97367,
    "folderId": null,
    "ownerUsername": "admin",
    "uploadedAt": 1778681486934
  },
  {
    "id": "1778681487997_be9jn7o",
    "name": "CamScanner 20-04-2026 10.35_104.jpg",
    "type": "photo",
    "telegramFileId": "AgACAgUAAxkDAAMdagSGj90o36m7YZwawxUl0tDryA4AAqESaxubMCFUc-llXbIjDnIBAAMCAAN3AAM7BA",
    "thumbTelegramFileId": null,
    "size": 933091,
    "folderId": null,
    "ownerUsername": "admin",
    "uploadedAt": 1778681487997
  },
  {
    "id": "1778681492283_qidt362",
    "name": "CamScanner 20-04-2026 10.35_105.jpg",
    "type": "photo",
    "telegramFileId": "AgACAgUAAxkDAAMeagSGk8h_5EaIIneeyvcwEnqrrnEAAqISaxubMCFUOe4bYaZXArQBAAMCAAN3AAM7BA",
    "thumbTelegramFileId": null,
    "size": 1121253,
    "folderId": null,
    "ownerUsername": "admin",
    "uploadedAt": 1778681492283
  },
  {
    "id": "1778681494850_lm6ysqo",
    "name": "CamScanner 20-04-2026 10.35_113.jpg",
    "type": "photo",
    "telegramFileId": "AgACAgUAAxkDAAMfagSGloPZZ5Fjq1GFjAuy0YizjyIAAqMSaxubMCFUpJgzyHgDo4cBAAMCAAN3AAM7BA",
    "thumbTelegramFileId": null,
    "size": 1170420,
    "folderId": null,
    "ownerUsername": "admin",
    "uploadedAt": 1778681494850
  },
  {
    "id": "1778681499045_d9wrvdi",
    "name": "CamScanner 20-04-2026 10.35_24.jpg",
    "type": "photo",
    "telegramFileId": "AgACAgUAAxkDAAMgagSGmpI7vMH8-OidKh0_yhoxRt0AAqQSaxubMCFUkPz8r8MpVAkBAAMCAAN3AAM7BA",
    "thumbTelegramFileId": null,
    "size": 1163237,
    "folderId": null,
    "ownerUsername": "admin",
    "uploadedAt": 1778681499045
  },
  {
    "id": "1778681507004_6q6mzlv",
    "name": "CamScanner 20-04-2026 10.35_25.jpg",
    "type": "photo",
    "telegramFileId": "AgACAgUAAxkDAAMhagSGoo5d0tpqIrPpu-Q-ODZzHq0AAqUSaxubMCFUhn563-g6iuEBAAMCAAN3AAM7BA",
    "thumbTelegramFileId": null,
    "size": 1958964,
    "folderId": null,
    "ownerUsername": "admin",
    "uploadedAt": 1778681507004
  },
  {
    "id": "1778681509642_9lhm94j",
    "name": "CamScanner 20-04-2026 10.35_51.jpg",
    "type": "photo",
    "telegramFileId": "AgACAgUAAxkDAAMiagSGpb_45uw4IWr_95rYtw1AkLoAAqYSaxubMCFUBKcud7UWTT8BAAMCAAN3AAM7BA",
    "thumbTelegramFileId": null,
    "size": 833551,
    "folderId": null,
    "ownerUsername": "admin",
    "uploadedAt": 1778681509642
  },
  {
    "id": "1778681513943_krk9q7m",
    "name": "CamScanner 20-04-2026 10.35_52.jpg",
    "type": "photo",
    "telegramFileId": "AgACAgUAAxkDAAMjagSGqSdjONT8qFRS2hDl-wABgXDbAAKoEmsbmzAhVAyjRzWkODQ-AQADAgADdwADOwQ",
    "thumbTelegramFileId": null,
    "size": 963802,
    "folderId": null,
    "ownerUsername": "admin",
    "uploadedAt": 1778681513943
  },
  {
    "id": "1778681517085_9h7uhfq",
    "name": "CamScanner 20-04-2026 10.35_53.jpg",
    "type": "photo",
    "telegramFileId": "AgACAgUAAxkDAAMkagSGrBdank0qKbcvfRuOTi-BiocAAqkSaxubMCFUgQoEjJqA8g8BAAMCAAN3AAM7BA",
    "thumbTelegramFileId": null,
    "size": 1839577,
    "folderId": null,
    "ownerUsername": "admin",
    "uploadedAt": 1778681517085
  },
  {
    "id": "1778681524656_v2fp9c4",
    "name": "CamScanner 20-04-2026 10.35_54.jpg",
    "type": "photo",
    "telegramFileId": "AgACAgUAAxkDAAMlagSGsziqKiCiya4AAeEUoMk0fhWTAAKqEmsbmzAhVLa9dRvN6tpGAQADAgADdwADOwQ",
    "thumbTelegramFileId": null,
    "size": 1971775,
    "folderId": null,
    "ownerUsername": "admin",
    "uploadedAt": 1778681524656
  },
  {
    "id": "1778681527524_ywf0tl2",
    "name": "CamScanner 20-04-2026 10.35_55.jpg",
    "type": "photo",
    "telegramFileId": "AgACAgUAAxkDAAMmagSGt1_qbtf9K5f4TOqVZzrh0GYAAqsSaxubMCFUzSsOP9YKyOgBAAMCAAN3AAM7BA",
    "thumbTelegramFileId": null,
    "size": 1792030,
    "folderId": null,
    "ownerUsername": "admin",
    "uploadedAt": 1778681527524
  },
  {
    "id": "1778681532672_3kggtg4",
    "name": "CamScanner 20-04-2026 10.35_56.jpg",
    "type": "photo",
    "telegramFileId": "AgACAgUAAxkDAAMnagSGvMI4WxiytrhaZ765L8AMnIQAAqwSaxubMCFUBDKbTpSPC7UBAAMCAAN3AAM7BA",
    "thumbTelegramFileId": null,
    "size": 1286212,
    "folderId": null,
    "ownerUsername": "admin",
    "uploadedAt": 1778681532672
  },
  {
    "id": "1778681538011_w65hwq9",
    "name": "CamScanner 20-04-2026 10.35_57.jpg",
    "type": "photo",
    "telegramFileId": "AgACAgUAAxkDAAMoagSGwT_-fukwoP6bjfVbilTft58AAq0SaxubMCFUCEvmU73HDSABAAMCAAN3AAM7BA",
    "thumbTelegramFileId": null,
    "size": 1275272,
    "folderId": null,
    "ownerUsername": "admin",
    "uploadedAt": 1778681538011
  },
  {
    "id": "1778681543461_w9q9r3m",
    "name": "CamScanner 20-04-2026 10.35_58.jpg",
    "type": "photo",
    "telegramFileId": "AgACAgUAAxkDAAMpagSGx5joPyGBQNL8deXKEyh_HuEAAq4SaxubMCFUSXlLciB_LNcBAAMCAAN3AAM7BA",
    "thumbTelegramFileId": null,
    "size": 1337168,
    "folderId": null,
    "ownerUsername": "admin",
    "uploadedAt": 1778681543461
  },
  {
    "id": "1778681545943_hq9egpm",
    "name": "CamScanner 20-04-2026 10.35_59.jpg",
    "type": "photo",
    "telegramFileId": "AgACAgUAAxkDAAMqagSGyYwGAAH8E7q4JEqL01hkhxcQAAKvEmsbmzAhVMJSToKOlt43AQADAgADdwADOwQ",
    "thumbTelegramFileId": null,
    "size": 1216051,
    "folderId": null,
    "ownerUsername": "admin",
    "uploadedAt": 1778681545943
  },
  {
    "id": "1778681549853_p0rap3h",
    "name": "CamScanner 20-04-2026 10.35_60.jpg",
    "type": "photo",
    "telegramFileId": "AgACAgUAAxkDAAMragSGzUIIA8RrJo0LX8tGtvSXO-0AArASaxubMCFUMjvN-AFcMaEBAAMCAAN3AAM7BA",
    "thumbTelegramFileId": null,
    "size": 1070952,
    "folderId": null,
    "ownerUsername": "admin",
    "uploadedAt": 1778681549853
  },
  {
    "id": "1778681551343_ks1lb55",
    "name": "CamScanner 20-04-2026 10.35_61.jpg",
    "type": "photo",
    "telegramFileId": "AgACAgUAAxkDAAMsagSGzoQRhRs62MyOsUXEay_IZjwAArESaxubMCFU94QUWEQmC0MBAAMCAAN3AAM7BA",
    "thumbTelegramFileId": null,
    "size": 1329075,
    "folderId": null,
    "ownerUsername": "admin",
    "uploadedAt": 1778681551343
  },
  {
    "id": "1778681557577_16mmqsx",
    "name": "CamScanner 20-04-2026 10.35_62.jpg",
    "type": "photo",
    "telegramFileId": "AgACAgUAAxkDAAMtagSG1dC56EQ2fWQ3UeLjEqW0pT8AArISaxubMCFU_lG8PaxV3SEBAAMCAAN3AAM7BA",
    "thumbTelegramFileId": null,
    "size": 1715114,
    "folderId": null,
    "ownerUsername": "admin",
    "uploadedAt": 1778681557577
  },
  {
    "id": "1778681560206_7ixek4k",
    "name": "CamScanner 20-04-2026 10.35_63.jpg",
    "type": "photo",
    "telegramFileId": "AgACAgUAAxkDAAMuagSG1wABpBOuGCq1NQt7IOSp2GzCAAKzEmsbmzAhVBhcuTv1nX5iAQADAgADdwADOwQ",
    "thumbTelegramFileId": null,
    "size": 1219614,
    "folderId": null,
    "ownerUsername": "admin",
    "uploadedAt": 1778681560206
  },
  {
    "id": "1778681565225_fkfr2m3",
    "name": "CamScanner 20-04-2026 10.35_64.jpg",
    "type": "photo",
    "telegramFileId": "AgACAgUAAxkDAAMvagSG3KDa9an-HC7VpH5FrhgWJ4AAArQSaxubMCFUjq-TWINI_60BAAMCAAN3AAM7BA",
    "thumbTelegramFileId": null,
    "size": 1313147,
    "folderId": null,
    "ownerUsername": "admin",
    "uploadedAt": 1778681565225
  },
  {
    "id": "1778681568315_pwds2fv",
    "name": "CamScanner 20-04-2026 10.35_65.jpg",
    "type": "photo",
    "telegramFileId": "AgACAgUAAxkDAAMwagSG32U1BaZQiJWDfVQ80RtdwJgAArUSaxubMCFUIV__zocu8DIBAAMCAAN3AAM7BA",
    "thumbTelegramFileId": null,
    "size": 1701676,
    "folderId": null,
    "ownerUsername": "admin",
    "uploadedAt": 1778681568315
  },
  {
    "id": "1778681574886_r0hu53t",
    "name": "CamScanner 20-04-2026 10.35_66.jpg",
    "type": "photo",
    "telegramFileId": "AgACAgUAAxkDAAMxagSG5skKP_bcKYH4oeHNRuRl4a0AArYSaxubMCFUKExWDIhHCVMBAAMCAAN3AAM7BA",
    "thumbTelegramFileId": null,
    "size": 1913094,
    "folderId": null,
    "ownerUsername": "admin",
    "uploadedAt": 1778681574886
  },
  {
    "id": "1778681577753_jt5ff9m",
    "name": "CamScanner 20-04-2026 10.35_67.jpg",
    "type": "photo",
    "telegramFileId": "AgACAgUAAxkDAAMyagSG6c-OuX3b8_b3JSRWAWEpO48AArcSaxubMCFUa3DJ0h9YrhoBAAMCAAN3AAM7BA",
    "thumbTelegramFileId": null,
    "size": 1859395,
    "folderId": null,
    "ownerUsername": "admin",
    "uploadedAt": 1778681577754
  },
  {
    "id": "1778681583118_l37x55k",
    "name": "CamScanner 20-04-2026 10.35_68.jpg",
    "type": "photo",
    "telegramFileId": "AgACAgUAAxkDAAMzagSG7ionOV92RkrF8fkMFQUS4XQAArgSaxubMCFUC_6A3n-RSqUBAAMCAAN3AAM7BA",
    "thumbTelegramFileId": null,
    "size": 1532278,
    "folderId": null,
    "ownerUsername": "admin",
    "uploadedAt": 1778681583118
  },
  {
    "id": "1778681585772_ao2mh3p",
    "name": "CamScanner 20-04-2026 10.35_69.jpg",
    "type": "photo",
    "telegramFileId": "AgACAgUAAxkDAAM0agSG8eUiOXDlMuA0PYsJafJwlXMAArkSaxubMCFUuIFOfg38_dQBAAMCAAN3AAM7BA",
    "thumbTelegramFileId": null,
    "size": 1342060,
    "folderId": null,
    "ownerUsername": "admin",
    "uploadedAt": 1778681585772
  },
  {
    "id": "1778681589190_7rdh5gb",
    "name": "CamScanner 20-04-2026 10.35_100.jpg",
    "type": "photo",
    "telegramFileId": "AgACAgUAAxkDAAM1agSG9IJ3a0UWJhA8G_bvpjDsNjgAAroSaxubMCFUQmqEmZI_e8oBAAMCAAN3AAM7BA",
    "thumbTelegramFileId": null,
    "size": 889609,
    "folderId": null,
    "ownerUsername": "admin",
    "uploadedAt": 1778681589191
  },
  {
    "id": "1778681591469_nuvo0jz",
    "name": "CamScanner 20-04-2026 10.35_101.jpg",
    "type": "photo",
    "telegramFileId": "AgACAgUAAxkDAAM2agSG9nkg9Rg846Ph63PePEDtTHUAArsSaxubMCFUac4zqbQSMuMBAAMCAAN3AAM7BA",
    "thumbTelegramFileId": null,
    "size": 1519918,
    "folderId": null,
    "ownerUsername": "admin",
    "uploadedAt": 1778681591469
  },
  {
    "id": "1778681597589_nsvnyvm",
    "name": "CamScanner 20-04-2026 10.35_102.jpg",
    "type": "photo",
    "telegramFileId": "AgACAgUAAxkDAAM3agSG_ZDAqy2d4TAAAcsTX3eAxbtiAAK8EmsbmzAhVFJZSvBEthEHAQADAgADdwADOwQ",
    "thumbTelegramFileId": null,
    "size": 1303042,
    "folderId": null,
    "ownerUsername": "admin",
    "uploadedAt": 1778681597589
  },
  {
    "id": "1778681602626_8vp55u2",
    "name": "CamScanner 20-04-2026 10.35_103.jpg",
    "type": "photo",
    "telegramFileId": "AgACAgUAAxkDAAM4agSHAhtG2TelTBeSv1_93uX7iJsAAr0SaxubMCFU7NgeomlG6-kBAAMCAAN3AAM7BA",
    "thumbTelegramFileId": null,
    "size": 1282790,
    "folderId": null,
    "ownerUsername": "admin",
    "uploadedAt": 1778681602626
  },
  {
    "id": "1778681608941_cts9yr2",
    "name": "CamScanner 20-04-2026 10.35_106.jpg",
    "type": "photo",
    "telegramFileId": "AgACAgUAAxkDAAM5agSHCORn0eekTjEz6GfKtBnoW6kAAr4SaxubMCFUTlCGBTzBTrkBAAMCAAN3AAM7BA",
    "thumbTelegramFileId": null,
    "size": 1341075,
    "folderId": null,
    "ownerUsername": "admin",
    "uploadedAt": 1778681608941
  },
  {
    "id": "1778681612578_1oaem3c",
    "name": "CamScanner 20-04-2026 10.35_107.jpg",
    "type": "photo",
    "telegramFileId": "AgACAgUAAxkDAAM6agSHC3SyyfVQxjBBLMp_r8gLW04AAr8SaxubMCFUNkBq83h9lD4BAAMCAAN3AAM7BA",
    "thumbTelegramFileId": null,
    "size": 1388650,
    "folderId": null,
    "ownerUsername": "admin",
    "uploadedAt": 1778681612578
  },
  {
    "id": "1778681615558_0okylja",
    "name": "CamScanner 20-04-2026 10.35_46.jpg",
    "type": "photo",
    "telegramFileId": "AgACAgUAAxkDAAM7agSHD0fym7Tkoac-EZA5GBYw_t8AAsASaxubMCFU4reTVHlA7zwBAAMCAAN3AAM7BA",
    "thumbTelegramFileId": null,
    "size": 687600,
    "folderId": null,
    "ownerUsername": "admin",
    "uploadedAt": 1778681615558
  },
  {
    "id": "1778681618044_dzzvshj",
    "name": "CamScanner 20-04-2026 10.35_47.jpg",
    "type": "photo",
    "telegramFileId": "AgACAgUAAxkDAAM8agSHETB4hSIb521ta1OmK7a5H8sAAsESaxubMCFUi_diJL29EjABAAMCAAN3AAM7BA",
    "thumbTelegramFileId": null,
    "size": 947124,
    "folderId": null,
    "ownerUsername": "admin",
    "uploadedAt": 1778681618044
  },
  {
    "id": "1778681621643_bbl2f7j",
    "name": "CamScanner 20-04-2026 10.35_96.jpg",
    "type": "photo",
    "telegramFileId": "AgACAgUAAxkDAAM9agSHFdlmv-hJR1kqpHGHXy7EmqAAAsISaxubMCFUs78gvgHCevIBAAMCAAN3AAM7BA",
    "thumbTelegramFileId": null,
    "size": 945136,
    "folderId": null,
    "ownerUsername": "admin",
    "uploadedAt": 1778681621643
  },
  {
    "id": "1778681623952_valfd0t",
    "name": "CamScanner 20-04-2026 10.35_98.jpg",
    "type": "photo",
    "telegramFileId": "AgACAgUAAxkDAAM-agSHFxkDd-QwXH0SdVSxGDnpjUsAAsMSaxubMCFU0gY6eRJWJLwBAAMCAAN3AAM7BA",
    "thumbTelegramFileId": null,
    "size": 1125283,
    "folderId": null,
    "ownerUsername": "admin",
    "uploadedAt": 1778681623952
  },
  {
    "id": "1778681628207_fjnxuqb",
    "name": "CamScanner 20-04-2026 10.35_99.jpg",
    "type": "photo",
    "telegramFileId": "AgACAgUAAxkDAAM_agSHG31P8MxTMsZx8F_L4BCt_ZYAAsQSaxubMCFUGTXrX6OFzLABAAMCAAN3AAM7BA",
    "thumbTelegramFileId": null,
    "size": 1118247,
    "folderId": null,
    "ownerUsername": "admin",
    "uploadedAt": 1778681628207
  },
  {
    "id": "1778681634079_aavvq8g",
    "name": "CamScanner 20-04-2026 10.35_112.jpg",
    "type": "photo",
    "telegramFileId": "AgACAgUAAxkDAANAagSHIWdjAAE-IPb8cP0nith7gMBwAALFEmsbmzAhVAb9gDHm6R1LAQADAgADdwADOwQ",
    "thumbTelegramFileId": null,
    "size": 1378492,
    "folderId": null,
    "ownerUsername": "admin",
    "uploadedAt": 1778681634079
  },
  {
    "id": "1778681636446_554merg",
    "name": "CamScanner 20-04-2026 10.35_48.jpg",
    "type": "photo",
    "telegramFileId": "AgACAgUAAxkDAANBagSHJG8aZ1wT1l0HGfyDYC6lJKkAAsYSaxubMCFUDzY7rDJwdS4BAAMCAAN3AAM7BA",
    "thumbTelegramFileId": null,
    "size": 820621,
    "folderId": null,
    "ownerUsername": "admin",
    "uploadedAt": 1778681636446
  },
  {
    "id": "1778681639953_j6ez6hi",
    "name": "CamScanner 20-04-2026 10.35_49.jpg",
    "type": "photo",
    "telegramFileId": "AgACAgUAAxkDAANCagSHJ0WoqWbsd1PUmtx5cs3ytxEAAscSaxubMCFU77GrrnTbA90BAAMCAAN3AAM7BA",
    "thumbTelegramFileId": null,
    "size": 968372,
    "folderId": null,
    "ownerUsername": "admin",
    "uploadedAt": 1778681639953
  },
  {
    "id": "1778681641076_8xivp2t",
    "name": "CamScanner 20-04-2026 10.35_70.jpg",
    "type": "photo",
    "telegramFileId": "AgACAgUAAxkDAANDagSHKARWhxsw0baNEFHITDe5H2sAAsgSaxubMCFUkYRlUHiUHzIBAAMCAAN3AAM7BA",
    "thumbTelegramFileId": null,
    "size": 1169818,
    "folderId": null,
    "ownerUsername": "admin",
    "uploadedAt": 1778681641076
  },
  {
    "id": "1778681644586_fyq3g2w",
    "name": "CamScanner 20-04-2026 10.35_71.jpg",
    "type": "photo",
    "telegramFileId": "AgACAgUAAxkDAANEagSHLIjflBPh52-HGvsLsRNH07kAAskSaxubMCFURWiS9DghSaIBAAMCAAN3AAM7BA",
    "thumbTelegramFileId": null,
    "size": 960397,
    "folderId": null,
    "ownerUsername": "admin",
    "uploadedAt": 1778681644586
  },
  {
    "id": "1778681647112_3am9uw8",
    "name": "CamScanner 20-04-2026 10.35_72.jpg",
    "type": "photo",
    "telegramFileId": "AgACAgUAAxkDAANFagSHLjVbZsUXK9HSiC8tlrj-byIAAsoSaxubMCFUCSxwwAVRiKABAAMCAAN3AAM7BA",
    "thumbTelegramFileId": null,
    "size": 896191,
    "folderId": null,
    "ownerUsername": "admin",
    "uploadedAt": 1778681647112
  },
  {
    "id": "1778681651747_p9gtcz8",
    "name": "CamScanner 20-04-2026 10.35_73.jpg",
    "type": "photo",
    "telegramFileId": "AgACAgUAAxkDAANGagSHMzVbjnu7VRJEl0jJWX8YYF8AAssSaxubMCFUfAHFTrFLx9gBAAMCAAN3AAM7BA",
    "thumbTelegramFileId": null,
    "size": 1297390,
    "folderId": null,
    "ownerUsername": "admin",
    "uploadedAt": 1778681651747
  },
  {
    "id": "1778681654323_6oevxf8",
    "name": "CamScanner 20-04-2026 10.35_74.jpg",
    "type": "photo",
    "telegramFileId": "AgACAgUAAxkDAANHagSHNTt5NVAHbu2af3a-P_jUHbQAAswSaxubMCFUVlDKa-HSHmYBAAMCAAN3AAM7BA",
    "thumbTelegramFileId": null,
    "size": 1491359,
    "folderId": null,
    "ownerUsername": "admin",
    "uploadedAt": 1778681654323
  },
  {
    "id": "1778686955361_4wchdn1",
    "name": "Untitled Note_1778686954044.txt",
    "type": "text",
    "telegramFileId": "BQACAgUAAxkDAANLagSb63iCBkO9HQxDemWla-tx7S0AAp4eAAKbMCFUyxSGK9-GW_E7BA",
    "size": 1247,
    "ownerUsername": "admin",
    "uploadedAt": 1778686955363
  }
]